instmodel/__init__.py
instmodel/instruction_model.py
instmodel/model.py
instmodel/training_utils.py
instmodel-0.7.0.dist-info/licenses/LICENSE
instmodel-0.7.0.dist-info/METADATA
instmodel-0.7.0.dist-info/WHEEL
instmodel-0.7.0.dist-info/top_level.txt
instmodel-0.7.0.dist-info/RECORD
