Metadata-Version: 2.4
Name: instmodel
Version: 0.7.0
Summary: A package that provides advanced coding tools for training and deploying AI
Home-page: https://github.com/Joaoprcf/instmodel
Author: Joao Ferreira
Author-email: joaoprcf@gmail.com
License: MIT
Classifier: License :: OSI Approved :: MIT License
Classifier: Programming Language :: Python :: 3
Classifier: Operating System :: OS Independent
License-File: LICENSE
Requires-Dist: tensorflow==2.17.0
Requires-Dist: numpy
Requires-Dist: pandas
Requires-Dist: scipy
Requires-Dist: scikit-learn
Dynamic: license-file
